multicoint/__init__.py
multicoint/critical_values.py
multicoint/regression.py
multicoint/simulation.py
multicoint/tests.py
multicoint/utils.py
tests/__init__.py
tests/test_multicoint.py
multicoint-1.0.0.dist-info/METADATA
multicoint-1.0.0.dist-info/WHEEL
multicoint-1.0.0.dist-info/top_level.txt
multicoint-1.0.0.dist-info/RECORD
