Metadata-Version: 2.4
Name: multicoint
Version: 1.0.0
Summary: Multicointegration analysis for I(1) and I(2) time series
Author-email: Dr Merwan Roudane <merwanroudane920@gmail.com>
License: MIT
Project-URL: Homepage, https://github.com/merwanroudane/multicoint
Project-URL: Repository, https://github.com/merwanroudane/multicoint
Project-URL: Bug Reports, https://github.com/merwanroudane/multicoint/issues
Keywords: econometrics,time-series,cointegration,multicointegration,I(2),unit-root,ADF
Classifier: Development Status :: 4 - Beta
Classifier: Intended Audience :: Science/Research
Classifier: Topic :: Scientific/Engineering :: Mathematics
Classifier: License :: OSI Approved :: MIT License
Classifier: Programming Language :: Python :: 3
Classifier: Programming Language :: Python :: 3.7
Classifier: Programming Language :: Python :: 3.8
Classifier: Programming Language :: Python :: 3.9
Classifier: Programming Language :: Python :: 3.10
Classifier: Programming Language :: Python :: 3.11
Requires-Python: >=3.7
Requires-Dist: numpy>=1.20.0
Requires-Dist: scipy>=1.7.0
Requires-Dist: pandas>=1.3.0
Requires-Dist: statsmodels>=0.13.0
Requires-Dist: matplotlib>=3.4.0
